saga_llm_evaluation/__init__.py
saga_llm_evaluation/helpers/__init__.py
saga_llm_evaluation/helpers/embedding_metrics.py
saga_llm_evaluation/helpers/language_metrics.py
saga_llm_evaluation/helpers/llm_metrics.py
saga_llm_evaluation/helpers/retrieval_metrics.py
saga_llm_evaluation/helpers/utils.py
saga_llm_evaluation/resources/__init__.py
saga_llm_evaluation/score.py
saga_llm_evaluation/scorer.json
saga_llm_evaluation-0.12.1.dist-info/METADATA
saga_llm_evaluation-0.12.1.dist-info/WHEEL
saga_llm_evaluation-0.12.1.dist-info/RECORD
