Metadata-Version: 2.1
Name: saga-llm-evaluation
Version: 0.12.1
Summary: Versatile Python library designed for evaluating the performance of large language models in Natural Language Processing (NLP) tasks. Developed by Sagacify
Author: Leonardo Remondini
Author-email: leonardo.remondini@sagacify.com
Requires-Python: >=3.9,<3.11
Classifier: Programming Language :: Python :: 3
Classifier: Programming Language :: Python :: 3.9
Classifier: Programming Language :: Python :: 3.10
Provides-Extra: scorer
Requires-Dist: bert-score (>=0.3.13,<0.4.0)
Requires-Dist: elemeta (>=1.0.7,<2.0.0) ; extra == "scorer"
Requires-Dist: evaluate (>=0.4.1,<0.5.0)
Requires-Dist: faiss-cpu (>=1.7.4,<2.0.0)
Requires-Dist: langchain (>=0.2.15,<0.3.0)
Requires-Dist: langchain-community (>=0.2.15,<0.3.0)
Requires-Dist: langchain-huggingface (>=0.0.3,<0.0.4)
Requires-Dist: langchain-openai (>=0.1.23,<0.2.0)
Requires-Dist: llama-cpp-python (>=0.2.11,<0.3.0)
Requires-Dist: llama-index (>=0.11.3,<0.12.0)
Requires-Dist: mauve-text (>=0.3.0,<0.4.0)
Requires-Dist: nltk (>=3.9.1,<4.0.0)
Requires-Dist: numpy (>=1.21.2,<2.0.0)
Requires-Dist: spacy (>=3.1.3,<4.0.0)
Requires-Dist: torch (==2.1.1)
Requires-Dist: transformers (>=4.21.1,<5.0.0)
